setup.py
jive_sdk/__init__.py
jive_sdk.egg-info/PKG-INFO
jive_sdk.egg-info/SOURCES.txt
jive_sdk.egg-info/dependency_links.txt
jive_sdk.egg-info/not-zip-safe
jive_sdk.egg-info/top_level.txt