Metadata-Version: 1.0
Name: jive-sdk
Version: 0.1
Summary: Useful tools for building microservices and Jive Add-Ons for Python PIP
Home-page: https://github.com/jivesoftware/jive-sdk-python-pip
Author: Jive Software (Open Source)
Author-email: jivedev@jivesoftware.com
License: MIT
Platform: UNKNOWN
